ud_mixpanel_api/__init__.py
ud_mixpanel_api/dataset_load_example.py
ud_mixpanel_api/datasets_examples.py
ud_mixpanel_api/mixpanel_api_example.py
ud_mixpanel_api/paginator.py
ud_mixpanel_api-0.2.dist-info/LICENSE
ud_mixpanel_api-0.2.dist-info/METADATA
ud_mixpanel_api-0.2.dist-info/WHEEL
ud_mixpanel_api-0.2.dist-info/top_level.txt
ud_mixpanel_api-0.2.dist-info/RECORD
