Metadata-Version: 2.1
Name: ud-mixpanel-api
Version: 0.2
Summary: Mixpanel API Package for Python 3
Home-page: UNKNOWN
Author: Sachin Dev
Author-email: hellosachindev@gmail.com
License: UNKNOWN
Platform: UNKNOWN
Classifier: Programming Language :: Python :: 3
Classifier: License :: OSI Approved :: MIT License
Classifier: Operating System :: OS Independent
Requires-Python: >=3.6
